{
  "todos": [
    {
      "id": 1697182461354,
      "title": "nmadur",
      "isFinished": false,
      "priority": "low"
    },
    {
      "id": 1697182480019,
      "title": "nmadur",
      "isFinished": false,
      "priority": "low"
    },
    {
      "id": 1697186753689,
      "title": "Assalomu alaykum",
      "isFinished": false,
      "priority": "low",
      "category": "today"
    },
    {
      "id": 1697186766153,
      "title": " ish",
      "isFinished": true,
      "priority": "low",
      "category": "tomorrow"
    },
    {
      "id": 1697186873058,
      "title": "asd",
      "isFinished": false,
      "priority": "low",
      "category": "today"
    },
    {
      "id": 1697187004600,
      "title": "Assalomu alaykum",
      "isFinished": false,
      "priority": "low",
      "category": "today"
    },
    {
      "id": 1697187016777,
      "title": "da",
      "isFinished": false,
      "priority": "low",
      "category": "others"
    },
    {
      "id": 1697187018939,
      "title": "da",
      "isFinished": false,
      "priority": "low",
      "category": "others"
    },
    {
      "id": 1697187020012,
      "title": "da",
      "isFinished": false,
      "priority": "low",
      "category": "others"
    }
  ]
}